SubAplicacion_Ventas/Descuentos.py
SubAplicacion_Ventas/Exceptions.py
SubAplicacion_Ventas/Gestor_Ventas.py
SubAplicacion_Ventas/Impuestos.py
SubAplicacion_Ventas/Precios.py
SubAplicacion_Ventas/__init__.py
Test_Aplicacion_Ventas/Test_Aplicacion_Ventas.py
Test_Aplicacion_Ventas/__init__.py
aplicacion_ventas_hc-0.1.0.dist-info/licenses/LICENCE
tests/Test_Aplicacion_Ventas.py
tests/__init__.py
aplicacion_ventas_hc-0.1.0.dist-info/METADATA
aplicacion_ventas_hc-0.1.0.dist-info/WHEEL
aplicacion_ventas_hc-0.1.0.dist-info/top_level.txt
aplicacion_ventas_hc-0.1.0.dist-info/RECORD
