Metadata-Version: 2.4
Name: aplicacion_ventas_hc
Version: 0.1.0
Summary: Paquete para administracion de ventas, precios, descuentos, impuestos
Home-page: https://github.com/curso_python_cce/gestor/aplicacionventas
Author: HC
Author-email: hcovas2017@gmail.com
Classifier: Programming Language :: Python :: 3
Classifier: Operating System :: OS Independent
Requires-Python: >=3.7
License-File: LICENCE
Dynamic: author
Dynamic: author-email
Dynamic: classifier
Dynamic: description
Dynamic: description-content-type
Dynamic: home-page
Dynamic: license-file
Dynamic: requires-python
Dynamic: summary
